{
  "project_info": {
    "project_number": "954455680455",
    "firebase_url": "https://enlist-duo.firebaseio.com",
    "project_id": "enlist-duo",
    "storage_bucket": "enlist-duo.appspot.com"
  },
  "client": [
    {
      "client_info": {
        "mobilesdk_app_id": "1:954455680455:android:55b1b6c0b5afb8465365e2",
        "android_client_info": {
          "package_name": "com.example.enlist"
        }
      },
      "oauth_client": [
        {
          "client_id": "954455680455-h883fp4i4osgmu13msa0sb9sph9dq0r8.apps.googleusercontent.com",
          "client_type": 3
        }
      ],
      "api_key": [
        {
          "current_key": "AIzaSyAIj0FqrGtNbE1Bpn9NMpg0Ba93dtlP6QE"
        }
      ],
      "services": {
        "appinvite_service": {
          "other_platform_oauth_client": [
            {
              "client_id": "954455680455-h883fp4i4osgmu13msa0sb9sph9dq0r8.apps.googleusercontent.com",
              "client_type": 3
            }
          ]
        }
      }
    }
  ],
  "configuration_version": "1"
}